patl/__init__.py
patl/commands.py
patl/core.py
patl/utils.py
Patl-0.0.1b0.dist-info/LICENCE
Patl-0.0.1b0.dist-info/METADATA
Patl-0.0.1b0.dist-info/WHEEL
Patl-0.0.1b0.dist-info/entry_points.txt
Patl-0.0.1b0.dist-info/top_level.txt
Patl-0.0.1b0.dist-info/RECORD
