Metadata-Version: 2.1
Name: Patl
Version: 0.0.1b0
Summary: Patl helps you in creating a monitorable structure for your files and folder of your big project.
Home-page: https://github.com/Ajay1290/patl
Author: Ajay Patil
Author-email: ajay.patil.a01@gmail.com
License: MIT License
Platform: UNKNOWN
